{
  "version": "4.0.0-beta.7",
  "flags": {},
  "checked": false,
  "shapes": [
    {
      "label": "Blue_Lasear",
      "score": null,
      "points": [
        [
          268.989898989899,
          288.8888888888889
        ]
      ],
      "group_id": null,
      "description": "",
      "difficult": false,
      "shape_type": "point",
      "flags": {},
      "attributes": {},
      "kie_linking": []
    },
    {
      "label": "Canvas",
      "score": null,
      "points": [
        [
          237.43185078909616,
          227.24533715925398
        ],
        [
          343.3142037302726,
          227.24533715925398
        ],
        [
          343.3142037302726,
          295.39454806312773
        ],
        [
          237.43185078909616,
          295.39454806312773
        ]
      ],
      "group_id": null,
      "description": "",
      "difficult": false,
      "shape_type": "rectangle",
      "flags": {},
      "attributes": {},
      "kie_linking": []
    }
  ],
  "imagePath": "laser_20260604_183250_694.jpg",
  "imageData": null,
  "imageHeight": 640,
  "imageWidth": 640,
  "description": ""
}